jupyterlab_judge/__init__.py
jupyterlab_judge/_version.py
jupyterlab_judge/handlers.py
jupyterlab_judge/yjudge.py
jupyterlab_judge/locale/ko_KR/LC_MESSAGES/jupyterlab_judge.json
jupyterlab_judge/locale/ko_KR/LC_MESSAGES/jupyterlab_judge.po
jupyterlab_judge/tests/__init__.py
jupyterlab_judge/tests/test_handlers.py
jupyterlab_judge-1.29.1.data/data/etc/jupyter/jupyter_server_config.d/jupyterlab_judge.json
jupyterlab_judge-1.29.1.data/data/share/jupyter/labextensions/jupyterlab-judge/package.json
jupyterlab_judge-1.29.1.data/data/share/jupyter/labextensions/jupyterlab-judge/schemas/jupyterlab-judge/package.json.orig
jupyterlab_judge-1.29.1.data/data/share/jupyter/labextensions/jupyterlab-judge/schemas/jupyterlab-judge/plugin.json
jupyterlab_judge-1.29.1.data/data/share/jupyter/labextensions/jupyterlab-judge/static/363.1234c077cde08f954669.js
jupyterlab_judge-1.29.1.data/data/share/jupyter/labextensions/jupyterlab-judge/static/377.618ae2027714b90d4194.js
jupyterlab_judge-1.29.1.data/data/share/jupyter/labextensions/jupyterlab-judge/static/531.2dddf260f4c4cedd1492.js
jupyterlab_judge-1.29.1.data/data/share/jupyter/labextensions/jupyterlab-judge/static/531.2dddf260f4c4cedd1492.js.LICENSE.txt
jupyterlab_judge-1.29.1.data/data/share/jupyter/labextensions/jupyterlab-judge/static/728.4883ab7d334ae50e7328.js
jupyterlab_judge-1.29.1.data/data/share/jupyter/labextensions/jupyterlab-judge/static/868.4e08da59506dd08e5fa3.js
jupyterlab_judge-1.29.1.data/data/share/jupyter/labextensions/jupyterlab-judge/static/872.f299ae914ffb40abcf6a.js
jupyterlab_judge-1.29.1.data/data/share/jupyter/labextensions/jupyterlab-judge/static/872.f299ae914ffb40abcf6a.js.LICENSE.txt
jupyterlab_judge-1.29.1.data/data/share/jupyter/labextensions/jupyterlab-judge/static/remoteEntry.bffe5f9d129d18f8febd.js
jupyterlab_judge-1.29.1.data/data/share/jupyter/labextensions/jupyterlab-judge/static/style.js
jupyterlab_judge-1.29.1.dist-info/METADATA
jupyterlab_judge-1.29.1.dist-info/WHEEL
jupyterlab_judge-1.29.1.dist-info/entry_points.txt
jupyterlab_judge-1.29.1.dist-info/licenses/LICENSE
jupyterlab_judge-1.29.1.dist-info/RECORD
