Metadata-Version: 2.4
Name: jupyterlab_judge
Version: 1.29.1
Dynamic: Keywords
Summary: A simple online judge for Jupyter Lab.
Project-URL: Homepage, https://github.com/team-monolith-product/jupyterlab-judge
Project-URL: Bug Tracker, https://github.com/team-monolith-product/jupyterlab-judge/issues
Project-URL: Repository, https://github.com/team-monolith-product/jupyterlab-judge.git
Author-email: ChangHwan Lee <lch@team-mono.com>
License: BSD 3-Clause License
License-File: LICENSE
Classifier: Framework :: Jupyter
Classifier: Framework :: Jupyter :: JupyterLab
Classifier: Framework :: Jupyter :: JupyterLab :: 4
Classifier: Framework :: Jupyter :: JupyterLab :: Extensions
Classifier: Framework :: Jupyter :: JupyterLab :: Extensions :: Prebuilt
Classifier: License :: OSI Approved :: BSD License
Classifier: Programming Language :: Python
Classifier: Programming Language :: Python :: 3
Classifier: Programming Language :: Python :: 3.8
Classifier: Programming Language :: Python :: 3.9
Classifier: Programming Language :: Python :: 3.10
Classifier: Programming Language :: Python :: 3.11
Requires-Python: >=3.8
Requires-Dist: jupyter-server<3,>=2.0.1
Provides-Extra: test
Requires-Dist: coverage; extra == 'test'
Requires-Dist: pytest; extra == 'test'
Requires-Dist: pytest-asyncio; extra == 'test'
Requires-Dist: pytest-cov; extra == 'test'
Requires-Dist: pytest-jupyter[server]>=0.6.0; extra == 'test'
